z_linus/__init__.py
z_linus/db.py
z_linus/log.py
z_linus/model.py
z_linus/server.py
z_linus/team.py
z_linus/agents/__init__.py
z_linus/agents/debuger/__init__.py
z_linus/agents/debuger/agent.py
z_linus/agents/debuger/toolkit.py
z_linus/agents/github/__init__.py
z_linus/agents/github/agent.py
z_linus/agents/github/toolkit.py
z_linus/agents/grammer/__init__.py
z_linus/agents/grammer/agent.py
z_linus/agents/grammer/toolkit.py
z_linus/agents/mcp_github_owner/__init__.py
z_linus/agents/mcp_github_owner/agent.py
z_linus/agents/mcp_github_owner/toolkit.py
z_linus/brain/__init__.py
z_linus/brain/agent.py
z_linus/brain/toolkit.py
z_linus-0.1.1.dist-info/METADATA
z_linus-0.1.1.dist-info/WHEEL
z_linus-0.1.1.dist-info/top_level.txt
z_linus-0.1.1.dist-info/RECORD
