Metadata-Version: 2.4
Name: z-linus
Version: 0.1.1
Summary: Add your description here
Requires-Python: >=3.12
Requires-Dist: agno>=2.3.21
Requires-Dist: anyio>=4.12.0
Requires-Dist: colorlog>=6.10.1
Requires-Dist: dotenv>=0.9.9
Requires-Dist: fastapi>=0.128.0
Requires-Dist: mcp>=1.25.0
Requires-Dist: pytest>=9.0.2
Requires-Dist: pytest-asyncio>=1.3.0
Requires-Dist: pytest-tornasync>=0.6.0.post2
Requires-Dist: requests>=2.32.5
Requires-Dist: toml>=0.10.2
Requires-Dist: uvicorn>=0.40.0
